{
  "__inputs": [
    {
      "name": "DS_ACONF",
      "label": "aconf",
      "description": "",
      "type": "datasource",
      "pluginId": "mysql",
      "pluginName": "MySQL"
    }
  ],
  "__elements": {},
  "__requires": [
    {
      "type": "grafana",
      "id": "grafana",
      "name": "Grafana",
      "version": "9.2.6"
    },
    {
      "type": "datasource",
      "id": "mysql",
      "name": "MySQL",
      "version": "1.0.0"
    },
    {
      "type": "panel",
      "id": "table",
      "name": "Table",
      "version": ""
    }
  ],
  "annotations": {
    "list": [
      {
        "builtIn": 1,
        "datasource": {
          "type": "datasource",
          "uid": "grafana"
        },
        "enable": true,
        "hide": true,
        "iconColor": "rgba(0, 211, 255, 1)",
        "name": "Annotations & Alerts",
        "target": {
          "limit": 100,
          "matchAny": false,
          "tags": [],
          "type": "dashboard"
        },
        "type": "dashboard"
      }
    ]
  },
  "editable": true,
  "fiscalYearStartMonth": 0,
  "graphTooltip": 0,
  "id": null,
  "links": [],
  "liveNow": false,
  "panels": [
    {
      "datasource": {
        "type": "mysql",
        "uid": "${DS_ACONF}"
      },
      "fieldConfig": {
        "defaults": {
          "color": {
            "mode": "thresholds"
          },
          "custom": {
            "align": "auto",
            "displayMode": "auto",
            "filterable": true,
            "inspect": false
          },
          "mappings": [],
          "thresholds": {
            "mode": "absolute",
            "steps": [
              {
                "color": "green",
                "value": null
              },
              {
                "color": "red",
                "value": 80
              }
            ]
          }
        },
        "overrides": [
          {
            "matcher": {
              "id": "byName",
              "options": "Origin"
            },
            "properties": [
              {
                "id": "custom.width",
                "value": 109
              }
            ]
          },
          {
            "matcher": {
              "id": "byName",
              "options": "pogo"
            },
            "properties": [
              {
                "id": "custom.width",
                "value": 70
              },
              {
                "id": "custom.displayMode",
                "value": "json-view"
              }
            ]
          },
          {
            "matcher": {
              "id": "byName",
              "options": "rgc"
            },
            "properties": [
              {
                "id": "custom.width",
                "value": 80
              }
            ]
          },
          {
            "matcher": {
              "id": "byName",
              "options": "PD"
            },
            "properties": [
              {
                "id": "custom.width",
                "value": 70
              },
              {
                "id": "custom.displayMode",
                "value": "json-view"
              }
            ]
          },
          {
            "matcher": {
              "id": "byName",
              "options": "RGC"
            },
            "properties": [
              {
                "id": "custom.width",
                "value": 70
              },
              {
                "id": "custom.displayMode",
                "value": "json-view"
              }
            ]
          },
          {
            "matcher": {
              "id": "byName",
              "options": "ip"
            },
            "properties": [
              {
                "id": "custom.width",
                "value": 109
              }
            ]
          },
          {
            "matcher": {
              "id": "byName",
              "options": "arch"
            },
            "properties": [
              {
                "id": "custom.width",
                "value": 68
              }
            ]
          },
          {
            "matcher": {
              "id": "byName",
              "options": "rom"
            },
            "properties": [
              {
                "id": "custom.width",
                "value": 70
              }
            ]
          },
          {
            "matcher": {
              "id": "byName",
              "options": "deviceID"
            },
            "properties": [
              {
                "id": "custom.width",
                "value": 126
              }
            ]
          },
          {
            "matcher": {
              "id": "byName",
              "options": "name"
            },
            "properties": [
              {
                "id": "custom.width",
                "value": 77
              }
            ]
          },
          {
            "matcher": {
              "id": "byName",
              "options": "instance"
            },
            "properties": [
              {
                "id": "custom.width",
                "value": 89
              }
            ]
          },
          {
            "matcher": {
              "id": "byName",
              "options": "macEth"
            },
            "properties": [
              {
                "id": "custom.width",
                "value": 150
              }
            ]
          },
          {
            "matcher": {
              "id": "byName",
              "options": "macWifi"
            },
            "properties": [
              {
                "id": "custom.width",
                "value": 17
              }
            ]
          },
          {
            "matcher": {
              "id": "byName",
              "options": "VM"
            },
            "properties": [
              {
                "id": "custom.width",
                "value": 70
              }
            ]
          },
          {
            "matcher": {
              "id": "byName",
              "options": "mitm"
            },
            "properties": [
              {
                "id": "custom.width",
                "value": 89
              }
            ]
          },
          {
            "matcher": {
              "id": "byName",
              "options": "VMdeviceID"
            },
            "properties": [
              {
                "id": "custom.width",
                "value": 131
              }
            ]
          },
          {
            "matcher": {
              "id": "byName",
              "options": "PDdeviceID"
            },
            "properties": [
              {
                "id": "custom.width",
                "value": 28
              }
            ]
          },
          {
            "matcher": {
              "id": "byName",
              "options": "hostname"
            },
            "properties": [
              {
                "id": "custom.width",
                "value": 127
              }
            ]
          },
          {
            "matcher": {
              "id": "byName",
              "options": "gmail"
            },
            "properties": [
              {
                "id": "custom.width",
                "value": 282
              }
            ]
          },
          {
            "matcher": {
              "id": "byName",
              "options": "productmodel"
            },
            "properties": [
              {
                "id": "custom.width",
                "value": 134
              }
            ]
          },
          {
            "matcher": {
              "id": "byName",
              "options": "vm_script"
            },
            "properties": [
              {
                "id": "custom.width",
                "value": 94
              }
            ]
          },
          {
            "matcher": {
              "id": "byName",
              "options": "42vmapper"
            },
            "properties": [
              {
                "id": "custom.width",
                "value": 107
              }
            ]
          },
          {
            "matcher": {
              "id": "byName",
              "options": "55vmapper"
            },
            "properties": [
              {
                "id": "custom.width",
                "value": 106
              }
            ]
          },
          {
            "matcher": {
              "id": "byName",
              "options": "diskSysPct"
            },
            "properties": [
              {
                "id": "custom.width",
                "value": 103
              }
            ]
          },
          {
            "matcher": {
              "id": "byName",
              "options": "diskDataPct"
            },
            "properties": [
              {
                "id": "custom.width",
                "value": 111
              }
            ]
          },
          {
            "matcher": {
              "id": "byName",
              "options": "numPogo"
            },
            "properties": [
              {
                "id": "custom.width",
                "value": 97
              }
            ]
          },
          {
            "matcher": {
              "id": "byName",
              "options": "lastUpdate"
            },
            "properties": [
              {
                "id": "custom.width",
                "value": 240
              }
            ]
          },
          {
            "matcher": {
              "id": "byName",
              "options": "42vm"
            },
            "properties": [
              {
                "id": "custom.width",
                "value": 76
              }
            ]
          },
          {
            "matcher": {
              "id": "byName",
              "options": "55vm"
            },
            "properties": [
              {
                "id": "custom.width",
                "value": 72
              }
            ]
          },
          {
            "matcher": {
              "id": "byName",
              "options": "wh"
            },
            "properties": [
              {
                "id": "custom.width",
                "value": 62
              }
            ]
          },
          {
            "matcher": {
              "id": "byName",
              "options": "temp"
            },
            "properties": [
              {
                "id": "custom.width",
                "value": 71
              }
            ]
          },
          {
            "matcher": {
              "id": "byName",
              "options": "deviceName"
            },
            "properties": [
              {
                "id": "custom.width",
                "value": 123
              }
            ]
          },
          {
            "matcher": {
              "id": "byName",
              "options": "atlasSh"
            },
            "properties": [
              {
                "id": "custom.width",
                "value": 89
              }
            ]
          },
          {
            "matcher": {
              "id": "byName",
              "options": "atls.sh"
            },
            "properties": [
              {
                "id": "custom.width",
                "value": 79
              }
            ]
          },
          {
            "matcher": {
              "id": "byName",
              "options": "playstore"
            },
            "properties": [
              {
                "id": "custom.width",
                "value": 79
              }
            ]
          },
          {
            "matcher": {
              "id": "byName",
              "options": "monitor"
            },
            "properties": [
              {
                "id": "custom.width",
                "value": 86
              }
            ]
          },
          {
            "matcher": {
              "id": "byName",
              "options": "atlas"
            },
            "properties": [
              {
                "id": "custom.width",
                "value": 93
              }
            ]
          },
          {
            "matcher": {
              "id": "byName",
              "options": "atlas.sh"
            },
            "properties": [
              {
                "id": "custom.width",
                "value": 91
              }
            ]
          }
        ]
      },
      "gridPos": {
        "h": 23,
        "w": 24,
        "x": 0,
        "y": 0
      },
      "id": 2,
      "options": {
        "footer": {
          "fields": "",
          "reducer": [
            "sum"
          ],
          "show": false
        },
        "showHeader": true,
        "sortBy": []
      },
      "pluginVersion": "9.2.6",
      "targets": [
        {
          "datasource": {
            "type": "mysql",
            "uid": "${DS_ACONF}"
          },
          "format": "table",
          "group": [],
          "metricColumn": "none",
          "rawQuery": true,
          "rawSql": "SELECT\na.deviceName,\nifnull(a.ip,'no_data') as 'ip',\nifnull(a.arch,'no_data') as 'arch',\nifnull(a.productmodel,'no_data') as 'productmodel',\nifnull(a.pogo,'no_data') as 'pogo',\nifnull(a.atlas,'no_data') as 'atlas',\natlasSh as 'atlas.sh',\n55atlas as '55vm',\nwhversion as 'wh',\nmonitor,\ndiskSysPct,\ndiskDataPct,\nnumPogo,\ntemperature as 'temp',\nconvert_tz(timestamp,@@session.time_zone, '+00:00') as 'lastUpdate'\n-- timestamp as 'lastUpdate'\nFROM ATVsummary a\nORDER BY a.deviceName ASC\n",
          "refId": "A",
          "select": [
            [
              {
                "params": [
                  "value"
                ],
                "type": "column"
              }
            ]
          ],
          "timeColumn": "time",
          "where": [
            {
              "name": "$__timeFilter",
              "params": [],
              "type": "macro"
            }
          ]
        }
      ],
      "title": "Device overview",
      "type": "table"
    }
  ],
  "schemaVersion": 37,
  "style": "dark",
  "tags": [],
  "templating": {
    "list": []
  },
  "time": {
    "from": "now-6h",
    "to": "now"
  },
  "timepicker": {
    "hidden": true
  },
  "timezone": "",
  "title": "22. Atlas device overview",
  "uid": "RVgxODPGz",
  "version": 5,
  "weekStart": ""
}
